{
    "contentBody": {
        "title": "Test authoring 2.0 - 1",
        "body": "<html><body>test body 1</body></html>",
        "excerpt": "test excerpt  1",
        "bannerImage": {
            "src": "/file-asset/Expresso1",
            "sprite": "Expresso1.jpeg",
            "type": "image/jpeg"
        }
    },
    "contentKey": "MCFXA42Q4MHNCKXER4YOLK4SE5KQ",
    "contentSpace": {
        "id": "0Zuxx000000009hCAA",
        "resourceUrl": "/services/data/v54.0/connect/cms/spaces/0Zuxx000000009hCAA"
    },
    "contentType": {
        "fullyQualifiedName": "news"
    },
    "createdBy": {
        "id": "005xx000001X7fNAAS",
        "resourceUrl": "/services/data/v54.0/chatter/users/005xx000001X7fNAAS"
    },
    "createdDate": "2021-06-04T09:13:35.000Z",
    "folder": {
        "id": "9Puxx0000004CSOCA2",
        "resourceUrl": "/services/data/v54.0/connect/cms/folders/9Puxx0000004CSOCA2"
    },
    "isPublished": false,
    "language": "en_US",
    "lastModifiedBy": {
        "id": "005xx000001X7fNAAS",
        "resourceUrl": "/services/data/v54.0/chatter/users/005xx000001X7fNAAS"
    },
    "lastModifiedDate": "2021-06-04T09:13:35.000Z",
    "managedContentId": "20Yxx0000011SjyEAE",
    "managedContentVariantId": "9Psxx0000004DrUCAU",
    "managedContentVersionId": "5OUxx0000004E1AGAU",
    "title": "Test authoring 2.0 - 1",
    "urlName": "testurl-1"
}
