{
    "count": 2,
    "currentPageToken": "0",
    "currentPageUrl": "/services/data/v53.0/ui-api/list-ui/Opportunity?pageSize=20&pageToken=0&q=this",
    "eTag": "697235176c4a4c52640913bd96e4ea69",
    "lists": [
        {
            "apiName": "ClosingThisMonth",
            "id": "00BT1000000tiA6MAI",
            "label": "Closing This Month",
            "listUiUrl": "/services/data/v53.0/ui-api/list-ui/Opportunity/ClosingThisMonth"
        },
        {
            "apiName": "NewThisWeek",
            "id": "00BT1000000tiAfMAI",
            "label": "New This Week",
            "listUiUrl": "/services/data/v53.0/ui-api/list-ui/Opportunity/NewThisWeek"
        }
    ],
    "nextPageToken": null,
    "nextPageUrl": null,
    "objectApiName": "Opportunity",
    "pageSize": 20,
    "previousPageToken": null,
    "previousPageUrl": null,
    "queryString": "this",
    "recentListsOnly": false
}
