{
    "apiName": "Opportunity",
    "childRelationships": {},
    "eTag": "40042b3a49212a36e6b254432c6e0fd2",
    "fields": {
        "Account": {
            "displayValue": "Seahawks",
            "value": {
                "apiName": "Account",
                "childRelationships": {},
                "eTag": "a78e4ba42c1b2786ac506122f829e43f",
                "fields": {
                    "Id": {
                        "displayValue": null,
                        "value": "001T1000001nL4UIAU"
                    },
                    "Name": {
                        "displayValue": null,
                        "value": "Seahawks"
                    }
                },
                "id": "001T1000001nL4UIAU",
                "lastModifiedById": "005T1000000HsOgIAK",
                "lastModifiedDate": "2020-12-01T20:05:07.000Z",
                "recordTypeId": "012000000000000AAA",
                "recordTypeInfo": null,
                "systemModstamp": "2020-12-01T20:05:07.000Z",
                "weakEtag": 1606853107000
            }
        },
        "AccountId": {
            "displayValue": null,
            "value": "001T1000001nL4UIAU"
        }
    },
    "id": "006T1000001rGQJIA2",
    "lastModifiedById": "005T1000000HsOgIAK",
    "lastModifiedDate": "2020-12-01T20:05:36.000Z",
    "recordTypeId": "012000000000000AAA",
    "recordTypeInfo": null,
    "systemModstamp": "2020-12-01T20:05:37.000Z",
    "weakEtag": 1606853137000
}
